remove_comments/__init__.py
remove_comments/main.py
remove_comments/remove_comments.py
remove_comments-1.0.0.dist-info/METADATA
remove_comments-1.0.0.dist-info/WHEEL
remove_comments-1.0.0.dist-info/top_level.txt
remove_comments-1.0.0.dist-info/RECORD
