Metadata-Version: 2.1
Name: remove-comments
Version: 1.0.0
Summary: A Python library to remove hash comments from code files
Home-page: https://github.com/ваш_логин/remove_comments
Author: Ваше Имя
Author-email: ваш_email@example.com
License: UNKNOWN
Platform: UNKNOWN
Classifier: Programming Language :: Python :: 3
Classifier: License :: OSI Approved :: MIT License
Classifier: Operating System :: OS Independent
Requires-Python: >=3.6
